ipf_dynamic_attributes/__init__.py
ipf_dynamic_attributes/configs/__init__.py
ipf_dynamic_attributes/configs/filters.py
ipf_dynamic_attributes/configs/rules.py
ipf_dynamic_attributes/configs/sync.py
ipf_dynamic_attributes/configs/values.py
ipf_dynamic_attributes/entry.py
ipf_dynamic_attributes/models.py
ipf_dynamic_attributes/sync.py
ipf_dynamic_attributes-1.2.6.dist-info/METADATA
ipf_dynamic_attributes-1.2.6.dist-info/WHEEL
ipf_dynamic_attributes-1.2.6.dist-info/entry_points.txt
ipf_dynamic_attributes-1.2.6.dist-info/licenses/LICENSE
ipf_dynamic_attributes-1.2.6.dist-info/RECORD
