Metadata-Version: 2.4
Name: ipf_dynamic_attributes
Version: 1.2.6
Summary: Automation to Create Dynamic Attributes in IP Fabric
License: MIT
License-File: LICENSE
Keywords: ipfabric,ip-fabric,community-fabric
Author: Solution Architecture
Author-email: solution.architecture@ipfabric.io
Requires-Python: >=3.9,<4.0
Classifier: License :: OSI Approved :: MIT License
Classifier: Programming Language :: Python :: 3
Classifier: Programming Language :: Python :: 3.9
Classifier: Programming Language :: Python :: 3.10
Classifier: Programming Language :: Python :: 3.11
Classifier: Programming Language :: Python :: 3.12
Classifier: Programming Language :: Python :: 3.13
Classifier: Programming Language :: Python :: 3.14
Provides-Extra: excel
Requires-Dist: ipfabric (>=7.2.0,<8.0.0)
Requires-Dist: pandas (>=2.2.3,<3.0.0)
Requires-Dist: pyyaml (>=6.0.2,<7.0.0)
Requires-Dist: pyyaml-include (>=2.2,<3.0)
Requires-Dist: tomli (>=2.0.0,<3.0.0) ; python_version < "3.11"
Requires-Dist: xlsxwriter (>=3.2.3,<4.0.0) ; extra == "excel"
Project-URL: Changelog, https://gitlab.com/ip-fabric/integrations/ipf-dynamic-attributes/-/blob/main/CHANGELOG.md
Project-URL: Documentation, https://docs.ipfabric.io/main/integrations/dynamic-attributes/
Project-URL: IP Fabric, https://ipfabric.io/
Project-URL: Repository, https://gitlab.com/ip-fabric/integrations/ipf-dynamic-attributes
